{
	"info": {
		"_postman_id": "jewelry-b2b-api-collection",
		"name": "Jewelry B2B API",
		"description": "Complete API collection for Jewelry B2B application with dummy data",
		"schema": "https://schema.getpostman.com/json/collection/v2.1.0/collection.json"
	},
	"item": [
		{
			"name": "Authentication",
			"item": [
				{
					"name": "Register Admin",
					"event": [
						{
							"listen": "test",
							"script": {
								"exec": [
									"if (pm.response.code === 201) {",
									"    const response = pm.response.json();",
									"    pm.environment.set(\"authToken\", response.data.token);",
									"    pm.environment.set(\"tenantId\", response.data.tenantId);",
									"    pm.environment.set(\"userId\", response.data._id);",
									"    console.log(\"Token saved:\", response.data.token);",
									"}"
								],
								"type": "text/javascript"
							}
						}
					],
					"request": {
						"method": "POST",
						"header": [
							{
								"key": "Content-Type",
								"value": "application/json"
							}
						],
						"body": {
							"mode": "raw",
							"raw": "{\n  \"name\": \"Dixit Chavada\",\n  \"email\": \"admin@jewelryshop.com\",\n  \"password\": \"Admin@123\"\n}"
						},
						"url": {
							"raw": "{{baseUrl}}/api/auth/register",
							"host": [
								"{{baseUrl}}"
							],
							"path": [
								"api",
								"auth",
								"register"
							]
						},
						"description": "Register first admin user (tenant owner)"
					},
					"response": []
				},
				{
					"name": "Login",
					"event": [
						{
							"listen": "test",
							"script": {
								"exec": [
									"if (pm.response.code === 200) {",
									"    const response = pm.response.json();",
									"    pm.environment.set(\"authToken\", response.data.token);",
									"    pm.environment.set(\"tenantId\", response.data.tenantId);",
									"    pm.environment.set(\"userId\", response.data._id);",
									"}"
								],
								"type": "text/javascript"
							}
						}
					],
					"request": {
						"method": "POST",
						"header": [
							{
								"key": "Content-Type",
								"value": "application/json"
							}
						],
						"body": {
							"mode": "raw",
							"raw": "{\n  \"email\": \"admin@jewelryshop.com\",\n  \"password\": \"Admin@123\"\n}"
						},
						"url": {
							"raw": "{{baseUrl}}/api/auth/login",
							"host": [
								"{{baseUrl}}"
							],
							"path": [
								"api",
								"auth",
								"login"
							]
						},
						"description": "Login with email and password"
					},
					"response": []
				},
				{
					"name": "Forgot Password",
					"request": {
						"method": "POST",
						"header": [
							{
								"key": "Content-Type",
								"value": "application/json"
							}
						],
						"body": {
							"mode": "raw",
							"raw": "{\n  \"email\": \"admin@jewelryshop.com\"\n}"
						},
						"url": {
							"raw": "{{baseUrl}}/api/auth/forgot-password",
							"host": [
								"{{baseUrl}}"
							],
							"path": [
								"api",
								"auth",
								"forgot-password"
							]
						}
					},
					"response": []
				},
				{
					"name": "Reset Password",
					"request": {
						"method": "POST",
						"header": [
							{
								"key": "Content-Type",
								"value": "application/json"
							}
						],
						"body": {
							"mode": "raw",
							"raw": "{\n  \"token\": \"reset_token_here\",\n  \"newPassword\": \"NewPassword@123\"\n}"
						},
						"url": {
							"raw": "{{baseUrl}}/api/auth/reset-password",
							"host": [
								"{{baseUrl}}"
							],
							"path": [
								"api",
								"auth",
								"reset-password"
							]
						}
					},
					"response": []
				}
			]
		},
		{
			"name": "Categories",
			"item": [
				{
					"name": "Get All Categories",
					"request": {
						"method": "GET",
						"header": [
							{
								"key": "Authorization",
								"value": "Bearer {{authToken}}"
							}
						],
						"url": {
							"raw": "{{baseUrl}}/api/categories",
							"host": [
								"{{baseUrl}}"
							],
							"path": [
								"api",
								"categories"
							]
						}
					},
					"response": []
				},
				{
					"name": "Create Category - Rings",
					"event": [
						{
							"listen": "test",
							"script": {
								"exec": [
									"if (pm.response.code === 201) {",
									"    const response = pm.response.json();",
									"    pm.environment.set(\"categoryId\", response.data._id);",
									"}"
								],
								"type": "text/javascript"
							}
						}
					],
					"request": {
						"method": "POST",
						"header": [
							{
								"key": "Authorization",
								"value": "Bearer {{authToken}}"
							},
							{
								"key": "Content-Type",
								"value": "application/json"
							}
						],
						"body": {
							"mode": "raw",
							"raw": "{\n  \"name\": \"Rings\",\n  \"description\": \"Beautiful gold and diamond rings for all occasions\"\n}"
						},
						"url": {
							"raw": "{{baseUrl}}/api/categories",
							"host": [
								"{{baseUrl}}"
							],
							"path": [
								"api",
								"categories"
							]
						}
					},
					"response": []
				},
				{
					"name": "Create Category - Necklace",
					"request": {
						"method": "POST",
						"header": [
							{
								"key": "Authorization",
								"value": "Bearer {{authToken}}"
							},
							{
								"key": "Content-Type",
								"value": "application/json"
							}
						],
						"body": {
							"mode": "raw",
							"raw": "{\n  \"name\": \"Necklace\",\n  \"description\": \"Elegant necklaces in gold, silver and platinum\"\n}"
						},
						"url": {
							"raw": "{{baseUrl}}/api/categories",
							"host": [
								"{{baseUrl}}"
							],
							"path": [
								"api",
								"categories"
							]
						}
					},
					"response": []
				},
				{
					"name": "Create Category - Bangles",
					"request": {
						"method": "POST",
						"header": [
							{
								"key": "Authorization",
								"value": "Bearer {{authToken}}"
							},
							{
								"key": "Content-Type",
								"value": "application/json"
							}
						],
						"body": {
							"mode": "raw",
							"raw": "{\n  \"name\": \"Bangles\",\n  \"description\": \"Traditional and modern bangles\"\n}"
						},
						"url": {
							"raw": "{{baseUrl}}/api/categories",
							"host": [
								"{{baseUrl}}"
							],
							"path": [
								"api",
								"categories"
							]
						}
					},
					"response": []
				},
				{
					"name": "Update Category",
					"request": {
						"method": "PUT",
						"header": [
							{
								"key": "Authorization",
								"value": "Bearer {{authToken}}"
							},
							{
								"key": "Content-Type",
								"value": "application/json"
							}
						],
						"body": {
							"mode": "raw",
							"raw": "{\n  \"name\": \"Rings Collection\",\n  \"description\": \"Premium rings collection with diamonds and gemstones\"\n}"
						},
						"url": {
							"raw": "{{baseUrl}}/api/categories/{{categoryId}}",
							"host": [
								"{{baseUrl}}"
							],
							"path": [
								"api",
								"categories",
								"{{categoryId}}"
							]
						}
					},
					"response": []
				},
				{
					"name": "Delete Category",
					"request": {
						"method": "DELETE",
						"header": [
							{
								"key": "Authorization",
								"value": "Bearer {{authToken}}"
							}
						],
						"url": {
							"raw": "{{baseUrl}}/api/categories/{{categoryId}}",
							"host": [
								"{{baseUrl}}"
							],
							"path": [
								"api",
								"categories",
								"{{categoryId}}"
							]
						}
					},
					"response": []
				}
			]
		},
		{
			"name": "Products",
			"item": [
				{
					"name": "Get All Products",
					"request": {
						"method": "GET",
						"header": [
							{
								"key": "Authorization",
								"value": "Bearer {{authToken}}"
							}
						],
						"url": {
							"raw": "{{baseUrl}}/api/products",
							"host": [
								"{{baseUrl}}"
							],
							"path": [
								"api",
								"products"
							]
						}
					},
					"response": []
				},
				{
					"name": "Get Single Product",
					"request": {
						"method": "GET",
						"header": [
							{
								"key": "Authorization",
								"value": "Bearer {{authToken}}"
							}
						],
						"url": {
							"raw": "{{baseUrl}}/api/products/{{productId}}",
							"host": [
								"{{baseUrl}}"
							],
							"path": [
								"api",
								"products",
								"{{productId}}"
							]
						}
					},
					"response": []
				},
				{
					"name": "Create Product - Royal Ring",
					"event": [
						{
							"listen": "test",
							"script": {
								"exec": [
									"if (pm.response.code === 201) {",
									"    const response = pm.response.json();",
									"    pm.environment.set(\"productId\", response.data._id);",
									"}"
								],
								"type": "text/javascript"
							}
						}
					],
					"request": {
						"method": "POST",
						"header": [
							{
								"key": "Authorization",
								"value": "Bearer {{authToken}}"
							},
							{
								"key": "Content-Type",
								"value": "application/json"
							}
						],
						"body": {
							"mode": "raw",
							"raw": "{\n  \"categoryId\": \"{{categoryId}}\",\n  \"name\": \"Royal Diamond Ring\",\n  \"designCode\": \"RDR-001\",\n  \"description\": \"Elegant royal diamond ring with intricate design\",\n  \"metalType\": \"Gold\"\n}"
						},
						"url": {
							"raw": "{{baseUrl}}/api/products",
							"host": [
								"{{baseUrl}}"
							],
							"path": [
								"api",
								"products"
							]
						}
					},
					"response": []
				},
				{
					"name": "Create Product - Necklace",
					"request": {
						"method": "POST",
						"header": [
							{
								"key": "Authorization",
								"value": "Bearer {{authToken}}"
							},
							{
								"key": "Content-Type",
								"value": "application/json"
							}
						],
						"body": {
							"mode": "raw",
							"raw": "{\n  \"categoryId\": \"{{categoryId}}\",\n  \"name\": \"Traditional Gold Necklace\",\n  \"designCode\": \"TGN-001\",\n  \"description\": \"Heavy traditional gold necklace with temple design\",\n  \"metalType\": \"Gold\"\n}"
						},
						"url": {
							"raw": "{{baseUrl}}/api/products",
							"host": [
								"{{baseUrl}}"
							],
							"path": [
								"api",
								"products"
							]
						}
					},
					"response": []
				},
				{
					"name": "Update Product",
					"request": {
						"method": "PUT",
						"header": [
							{
								"key": "Authorization",
								"value": "Bearer {{authToken}}"
							},
							{
								"key": "Content-Type",
								"value": "application/json"
							}
						],
						"body": {
							"mode": "raw",
							"raw": "{\n  \"name\": \"Royal Diamond Ring Premium\",\n  \"description\": \"Premium royal diamond ring with 18K gold\"\n}"
						},
						"url": {
							"raw": "{{baseUrl}}/api/products/{{productId}}",
							"host": [
								"{{baseUrl}}"
							],
							"path": [
								"api",
								"products",
								"{{productId}}"
							]
						}
					},
					"response": []
				},
				{
					"name": "Delete Product",
					"request": {
						"method": "DELETE",
						"header": [
							{
								"key": "Authorization",
								"value": "Bearer {{authToken}}"
							}
						],
						"url": {
							"raw": "{{baseUrl}}/api/products/{{productId}}",
							"host": [
								"{{baseUrl}}"
							],
							"path": [
								"api",
								"products",
								"{{productId}}"
							]
						}
					},
					"response": []
				}
			]
		},
		{
			"name": "Product Variants",
			"item": [
				{
					"name": "Get All Variants",
					"request": {
						"method": "GET",
						"header": [
							{
								"key": "Authorization",
								"value": "Bearer {{authToken}}"
							}
						],
						"url": {
							"raw": "{{baseUrl}}/api/variants",
							"host": [
								"{{baseUrl}}"
							],
							"path": [
								"api",
								"variants"
							]
						}
					},
					"response": []
				},
				{
					"name": "Get Variants by Product",
					"request": {
						"method": "GET",
						"header": [
							{
								"key": "Authorization",
								"value": "Bearer {{authToken}}"
							}
						],
						"url": {
							"raw": "{{baseUrl}}/api/variants?productId={{productId}}",
							"host": [
								"{{baseUrl}}"
							],
							"path": [
								"api",
								"variants"
							],
							"query": [
								{
									"key": "productId",
									"value": "{{productId}}"
								}
							]
						}
					},
					"response": []
				},
				{
					"name": "Get Single Variant",
					"request": {
						"method": "GET",
						"header": [
							{
								"key": "Authorization",
								"value": "Bearer {{authToken}}"
							}
						],
						"url": {
							"raw": "{{baseUrl}}/api/variants/{{variantId}}",
							"host": [
								"{{baseUrl}}"
							],
							"path": [
								"api",
								"variants",
								"{{variantId}}"
							]
						}
					},
					"response": []
				},
				{
					"name": "Create Variant - 22K Gold",
					"event": [
						{
							"listen": "test",
							"script": {
								"exec": [
									"if (pm.response.code === 201) {",
									"    const response = pm.response.json();",
									"    pm.environment.set(\"variantId\", response.data._id);",
									"}"
								],
								"type": "text/javascript"
							}
						}
					],
					"request": {
						"method": "POST",
						"header": [
							{
								"key": "Authorization",
								"value": "Bearer {{authToken}}"
							},
							{
								"key": "Content-Type",
								"value": "application/json"
							}
						],
						"body": {
							"mode": "raw",
							"raw": "{\n  \"productId\": \"{{productId}}\",\n  \"sku\": \"RDR-001-22K-5G\",\n  \"purity\": \"22K\",\n  \"grossWeight\": 5.5,\n  \"netWeight\": 5,\n  \"stoneWeight\": 0.5,\n  \"metalRate\": 5800,\n  \"makingChargeType\": \"PerGram\",\n  \"makingChargeValue\": 600,\n  \"wastagePercentage\": 10,\n  \"stonePrice\": 8000,\n  \"gstPercentage\": 3,\n  \"stockQty\": 15,\n  \"attributes\": {\n    \"size\": \"7\",\n    \"color\": \"Yellow Gold\",\n    \"weight\": \"Light\"\n  },\n  \"images\": [\n    \"ring-front.jpg\",\n    \"ring-side.jpg\",\n    \"ring-top.jpg\"\n  ]\n}"
						},
						"url": {
							"raw": "{{baseUrl}}/api/variants",
							"host": [
								"{{baseUrl}}"
							],
							"path": [
								"api",
								"variants"
							]
						}
					},
					"response": []
				},
				{
					"name": "Create Variant - 18K Gold",
					"request": {
						"method": "POST",
						"header": [
							{
								"key": "Authorization",
								"value": "Bearer {{authToken}}"
							},
							{
								"key": "Content-Type",
								"value": "application/json"
							}
						],
						"body": {
							"mode": "raw",
							"raw": "{\n  \"productId\": \"{{productId}}\",\n  \"sku\": \"RDR-001-18K-5G\",\n  \"purity\": \"18K\",\n  \"grossWeight\": 5.5,\n  \"netWeight\": 5,\n  \"stoneWeight\": 0.5,\n  \"metalRate\": 4800,\n  \"makingChargeType\": \"PerGram\",\n  \"makingChargeValue\": 500,\n  \"wastagePercentage\": 8,\n  \"stonePrice\": 8000,\n  \"gstPercentage\": 3,\n  \"stockQty\": 20,\n  \"attributes\": {\n    \"size\": \"7\",\n    \"color\": \"Rose Gold\",\n    \"weight\": \"Light\"\n  },\n  \"images\": [\n    \"ring-rose-front.jpg\",\n    \"ring-rose-side.jpg\"\n  ]\n}"
						},
						"url": {
							"raw": "{{baseUrl}}/api/variants",
							"host": [
								"{{baseUrl}}"
							],
							"path": [
								"api",
								"variants"
							]
						}
					},
					"response": []
				},
				{
					"name": "Create Variant - Necklace",
					"request": {
						"method": "POST",
						"header": [
							{
								"key": "Authorization",
								"value": "Bearer {{authToken}}"
							},
							{
								"key": "Content-Type",
								"value": "application/json"
							}
						],
						"body": {
							"mode": "raw",
							"raw": "{\n  \"productId\": \"{{productId}}\",\n  \"sku\": \"TGN-001-22K-50G\",\n  \"purity\": \"22K\",\n  \"grossWeight\": 52.5,\n  \"netWeight\": 50,\n  \"stoneWeight\": 2.5,\n  \"metalRate\": 5800,\n  \"makingChargeType\": \"PerGram\",\n  \"makingChargeValue\": 700,\n  \"wastagePercentage\": 12,\n  \"stonePrice\": 15000,\n  \"gstPercentage\": 3,\n  \"stockQty\": 8,\n  \"attributes\": {\n    \"length\": \"18 inches\",\n    \"design\": \"Temple\",\n    \"weight\": \"Heavy\"\n  },\n  \"images\": [\n    \"necklace-1.jpg\",\n    \"necklace-2.jpg\"\n  ]\n}"
						},
						"url": {
							"raw": "{{baseUrl}}/api/variants",
							"host": [
								"{{baseUrl}}"
							],
							"path": [
								"api",
								"variants"
							]
						}
					},
					"response": []
				},
				{
					"name": "Update Variant",
					"request": {
						"method": "PUT",
						"header": [
							{
								"key": "Authorization",
								"value": "Bearer {{authToken}}"
							},
							{
								"key": "Content-Type",
								"value": "application/json"
							}
						],
						"body": {
							"mode": "raw",
							"raw": "{\n  \"metalRate\": 6000,\n  \"stockQty\": 20\n}"
						},
						"url": {
							"raw": "{{baseUrl}}/api/variants/{{variantId}}",
							"host": [
								"{{baseUrl}}"
							],
							"path": [
								"api",
								"variants",
								"{{variantId}}"
							]
						}
					},
					"response": []
				},
				{
					"name": "Update Stock Only",
					"request": {
						"method": "PATCH",
						"header": [
							{
								"key": "Authorization",
								"value": "Bearer {{authToken}}"
							},
							{
								"key": "Content-Type",
								"value": "application/json"
							}
						],
						"body": {
							"mode": "raw",
							"raw": "{\n  \"stockQty\": 25\n}"
						},
						"url": {
							"raw": "{{baseUrl}}/api/variants/{{variantId}}/stock",
							"host": [
								"{{baseUrl}}"
							],
							"path": [
								"api",
								"variants",
								"{{variantId}}",
								"stock"
							]
						}
					},
					"response": []
				},
				{
					"name": "Delete Variant",
					"request": {
						"method": "DELETE",
						"header": [
							{
								"key": "Authorization",
								"value": "Bearer {{authToken}}"
							}
						],
						"url": {
							"raw": "{{baseUrl}}/api/variants/{{variantId}}",
							"host": [
								"{{baseUrl}}"
							],
							"path": [
								"api",
								"variants",
								"{{variantId}}"
							]
						}
					},
					"response": []
				}
			]
		},
		{
			"name": "Customers",
			"item": [
				{
					"name": "Get All Customers",
					"request": {
						"method": "GET",
						"header": [
							{
								"key": "Authorization",
								"value": "Bearer {{authToken}}"
							}
						],
						"url": {
							"raw": "{{baseUrl}}/api/customers",
							"host": [
								"{{baseUrl}}"
							],
							"path": [
								"api",
								"customers"
							]
						}
					},
					"response": []
				},
				{
					"name": "Get Single Customer",
					"request": {
						"method": "GET",
						"header": [
							{
								"key": "Authorization",
								"value": "Bearer {{authToken}}"
							}
						],
						"url": {
							"raw": "{{baseUrl}}/api/customers/{{customerId}}",
							"host": [
								"{{baseUrl}}"
							],
							"path": [
								"api",
								"customers",
								"{{customerId}}"
							]
						}
					},
					"response": []
				},
				{
					"name": "Create Customer - Rajesh Jewelers",
					"event": [
						{
							"listen": "test",
							"script": {
								"exec": [
									"if (pm.response.code === 201) {",
									"    const response = pm.response.json();",
									"    pm.environment.set(\"customerId\", response.data._id);",
									"}"
								],
								"type": "text/javascript"
							}
						}
					],
					"request": {
						"method": "POST",
						"header": [
							{
								"key": "Authorization",
								"value": "Bearer {{authToken}}"
							},
							{
								"key": "Content-Type",
								"value": "application/json"
							}
						],
						"body": {
							"mode": "raw",
							"raw": "{\n  \"name\": \"Rajesh Kumar\",\n  \"mobile\": \"9876543210\",\n  \"email\": \"rajesh@jewelersltd.com\",\n  \"shopName\": \"Rajesh Jewelers Pvt Ltd\",\n  \"gstNumber\": \"27AABCU9603R1ZM\",\n  \"address\": {\n    \"line1\": \"Shop No 45, Zaveri Bazaar\",\n    \"city\": \"Mumbai\",\n    \"state\": \"Maharashtra\",\n    \"pincode\": \"400002\"\n  }\n}"
						},
						"url": {
							"raw": "{{baseUrl}}/api/customers",
							"host": [
								"{{baseUrl}}"
							],
							"path": [
								"api",
								"customers"
							]
						}
					},
					"response": []
				},
				{
					"name": "Create Customer - Surat Gold",
					"request": {
						"method": "POST",
						"header": [
							{
								"key": "Authorization",
								"value": "Bearer {{authToken}}"
							},
							{
								"key": "Content-Type",
								"value": "application/json"
							}
						],
						"body": {
							"mode": "raw",
							"raw": "{\n  \"name\": \"Mehul Shah\",\n  \"mobile\": \"9998887776\",\n  \"email\": \"mehul@suratgold.com\",\n  \"shopName\": \"Surat Gold Palace\",\n  \"gstNumber\": \"24AABCS1234F1Z5\",\n  \"address\": {\n    \"line1\": \"123, Ring Road\",\n    \"city\": \"Surat\",\n    \"state\": \"Gujarat\",\n    \"pincode\": \"395003\"\n  }\n}"
						},
						"url": {
							"raw": "{{baseUrl}}/api/customers",
							"host": [
								"{{baseUrl}}"
							],
							"path": [
								"api",
								"customers"
							]
						}
					},
					"response": []
				},
				{
					"name": "Create Customer - Ahmedabad Jewels",
					"request": {
						"method": "POST",
						"header": [
							{
								"key": "Authorization",
								"value": "Bearer {{authToken}}"
							},
							{
								"key": "Content-Type",
								"value": "application/json"
							}
						],
						"body": {
							"mode": "raw",
							"raw": "{\n  \"name\": \"Kiran Patel\",\n  \"mobile\": \"9825123456\",\n  \"email\": \"kiran@amdavadjewels.com\",\n  \"shopName\": \"Ahmedabad Jewels\",\n  \"gstNumber\": \"24AABCP1234G1Z8\",\n  \"address\": {\n    \"line1\": \"CG Road, Near Stadium\",\n    \"city\": \"Ahmedabad\",\n    \"state\": \"Gujarat\",\n    \"pincode\": \"380009\"\n  }\n}"
						},
						"url": {
							"raw": "{{baseUrl}}/api/customers",
							"host": [
								"{{baseUrl}}"
							],
							"path": [
								"api",
								"customers"
							]
						}
					},
					"response": []
				},
				{
					"name": "Update Customer",
					"request": {
						"method": "PUT",
						"header": [
							{
								"key": "Authorization",
								"value": "Bearer {{authToken}}"
							},
							{
								"key": "Content-Type",
								"value": "application/json"
							}
						],
						"body": {
							"mode": "raw",
							"raw": "{\n  \"mobile\": \"9876543211\",\n  \"email\": \"rajesh.new@jewelersltd.com\"\n}"
						},
						"url": {
							"raw": "{{baseUrl}}/api/customers/{{customerId}}",
							"host": [
								"{{baseUrl}}"
							],
							"path": [
								"api",
								"customers",
								"{{customerId}}"
							]
						}
					},
					"response": []
				},
				{
					"name": "Delete Customer",
					"request": {
						"method": "DELETE",
						"header": [
							{
								"key": "Authorization",
								"value": "Bearer {{authToken}}"
							}
						],
						"url": {
							"raw": "{{baseUrl}}/api/customers/{{customerId}}",
							"host": [
								"{{baseUrl}}"
							],
							"path": [
								"api",
								"customers",
								"{{customerId}}"
							]
						}
					},
					"response": []
				}
			]
		},
		{
			"name": "Orders",
			"item": [
				{
					"name": "Get All Orders",
					"request": {
						"method": "GET",
						"header": [
							{
								"key": "Authorization",
								"value": "Bearer {{authToken}}"
							}
						],
						"url": {
							"raw": "{{baseUrl}}/api/orders",
							"host": [
								"{{baseUrl}}"
							],
							"path": [
								"api",
								"orders"
							]
						}
					},
					"response": []
				},
				{
					"name": "Get Single Order with Items",
					"request": {
						"method": "GET",
						"header": [
							{
								"key": "Authorization",
								"value": "Bearer {{authToken}}"
							}
						],
						"url": {
							"raw": "{{baseUrl}}/api/orders/{{orderId}}",
							"host": [
								"{{baseUrl}}"
							],
							"path": [
								"api",
								"orders",
								"{{orderId}}"
							]
						}
					},
					"response": []
				},
				{
					"name": "Create Order - Single Item",
					"event": [
						{
							"listen": "test",
							"script": {
								"exec": [
									"if (pm.response.code === 201) {",
									"    const response = pm.response.json();",
									"    pm.environment.set(\"orderId\", response.data.order._id);",
									"}"
								],
								"type": "text/javascript"
							}
						}
					],
					"request": {
						"method": "POST",
						"header": [
							{
								"key": "Authorization",
								"value": "Bearer {{authToken}}"
							},
							{
								"key": "Content-Type",
								"value": "application/json"
							}
						],
						"body": {
							"mode": "raw",
							"raw": "{\n  \"customerId\": \"{{customerId}}\",\n  \"items\": [\n    {\n      \"variantId\": \"{{variantId}}\",\n      \"quantity\": 3\n    }\n  ],\n  \"paidAmount\": 50000,\n  \"notes\": \"Urgent delivery required by next week\"\n}"
						},
						"url": {
							"raw": "{{baseUrl}}/api/orders",
							"host": [
								"{{baseUrl}}"
							],
							"path": [
								"api",
								"orders"
							]
						}
					},
					"response": []
				},
				{
					"name": "Create Order - Multiple Items",
					"request": {
						"method": "POST",
						"header": [
							{
								"key": "Authorization",
								"value": "Bearer {{authToken}}"
							},
							{
								"key": "Content-Type",
								"value": "application/json"
							}
						],
						"body": {
							"mode": "raw",
							"raw": "{\n  \"customerId\": \"{{customerId}}\",\n  \"items\": [\n    {\n      \"variantId\": \"{{variantId}}\",\n      \"quantity\": 2\n    },\n    {\n      \"variantId\": \"{{variantId}}\",\n      \"quantity\": 5\n    }\n  ],\n  \"paidAmount\": 100000,\n  \"notes\": \"Wedding order - deliver by 15th\"\n}"
						},
						"url": {
							"raw": "{{baseUrl}}/api/orders",
							"host": [
								"{{baseUrl}}"
							],
							"path": [
								"api",
								"orders"
							]
						}
					},
					"response": []
				},
				{
					"name": "Update Order Status",
					"request": {
						"method": "PUT",
						"header": [
							{
								"key": "Authorization",
								"value": "Bearer {{authToken}}"
							},
							{
								"key": "Content-Type",
								"value": "application/json"
							}
						],
						"body": {
							"mode": "raw",
							"raw": "{\n  \"orderStatus\": \"Processing\",\n  \"paidAmount\": 75000\n}"
						},
						"url": {
							"raw": "{{baseUrl}}/api/orders/{{orderId}}",
							"host": [
								"{{baseUrl}}"
							],
							"path": [
								"api",
								"orders",
								"{{orderId}}"
							]
						}
					},
					"response": []
				},
				{
					"name": "Mark Order Complete",
					"request": {
						"method": "PUT",
						"header": [
							{
								"key": "Authorization",
								"value": "Bearer {{authToken}}"
							},
							{
								"key": "Content-Type",
								"value": "application/json"
							}
						],
						"body": {
							"mode": "raw",
							"raw": "{\n  \"orderStatus\": \"Completed\",\n  \"paymentStatus\": \"Paid\"\n}"
						},
						"url": {
							"raw": "{{baseUrl}}/api/orders/{{orderId}}",
							"host": [
								"{{baseUrl}}"
							],
							"path": [
								"api",
								"orders",
								"{{orderId}}"
							]
						}
					},
					"response": []
				},
				{
					"name": "Cancel Order (Restores Stock)",
					"request": {
						"method": "DELETE",
						"header": [
							{
								"key": "Authorization",
								"value": "Bearer {{authToken}}"
							}
						],
						"url": {
							"raw": "{{baseUrl}}/api/orders/{{orderId}}",
							"host": [
								"{{baseUrl}}"
							],
							"path": [
								"api",
								"orders",
								"{{orderId}}"
							]
						}
					},
					"response": []
				}
			]
		},
		{
			"name": "Dashboard",
			"item": [
				{
					"name": "Get Dashboard Statistics",
					"request": {
						"method": "GET",
						"header": [
							{
								"key": "Authorization",
								"value": "Bearer {{authToken}}"
							}
						],
						"url": {
							"raw": "{{baseUrl}}/api/dashboard",
							"host": [
								"{{baseUrl}}"
							],
							"path": [
								"api",
								"dashboard"
							]
						}
					},
					"response": []
				}
			]
		}
	],
	"event": [
		{
			"listen": "prerequest",
			"script": {
				"type": "text/javascript",
				"exec": [
					""
				]
			}
		},
		{
			"listen": "test",
			"script": {
				"type": "text/javascript",
				"exec": [
					""
				]
			}
		}
	],
	"variable": [
		{
			"key": "baseUrl",
			"value": "http://localhost:3000",
			"type": "string"
		}
	]
}

